saltimbanque/__init__.py
saltimbanque/__main__.py
saltimbanque/app.py
saltimbanque/pdf.py
saltimbanque/png.py
saltimbanque-1.2.1.dist-info/COPYING
saltimbanque-1.2.1.dist-info/METADATA
saltimbanque-1.2.1.dist-info/WHEEL
saltimbanque-1.2.1.dist-info/entry_points.txt
saltimbanque-1.2.1.dist-info/top_level.txt
saltimbanque-1.2.1.dist-info/RECORD
