Metadata-Version: 2.1
Name: saltimbanque
Version: 1.2.1
Summary: Provides an API to convert web pages to PDF
Author: Wanadev
Author-email: contact@wanadev.fr
Maintainer: Fabien LOISON
License: AGPLv3
License-File: COPYING
Requires-Dist: Flask
Requires-Dist: WeasyPrint
Provides-Extra: dev
Requires-Dist: nox; extra == "dev"
Requires-Dist: flake8; extra == "dev"
Requires-Dist: black; extra == "dev"
